primostest/__init__.py
primostest-1.0.dist-info/LICENSE.rst
primostest-1.0.dist-info/METADATA
primostest-1.0.dist-info/WHEEL
primostest-1.0.dist-info/top_level.txt
primostest-1.0.dist-info/RECORD
