Metadata-Version: 2.1
Name: primostest
Version: 1.0
Summary: Programa para calcular números primos de un rango determinado
Home-page: UNKNOWN
Author: Yonti Testa
Author-email: desprogramaci@gmail.com
License: GPL
Keywords: operaciones matemáticas
Platform: UNKNOWN
Classifier: Development Status :: 4 - Beta
Classifier: Intended Audience :: Developers
Classifier: Topic :: Utilities
Classifier: License :: OSI Approved :: GNU General Public License v3 (GPLv3)
Classifier: Programming Language :: Python :: 3
Classifier: Operating System :: OS Independent
